darx_core/__init__.py
darx_core/clients/__init__.py
darx_core/clients/slack.py
darx_core/clients/storage.py
darx_core/clients/supabase.py
darx_core/middleware/__init__.py
darx_core/utils/__init__.py
darx_core/utils/errors.py
darx_core/utils/idempotency.py
darx_core/utils/logging.py
darx_core/utils/retry.py
darx_core-0.1.0.dist-info/METADATA
darx_core-0.1.0.dist-info/WHEEL
darx_core-0.1.0.dist-info/top_level.txt
darx_core-0.1.0.dist-info/RECORD
