Metadata-Version: 2.4
Name: darx-core
Version: 0.1.0
Summary: Shared utilities and clients for DARX microservices
Home-page: https://github.com/digitalarchitex/darx-core
Author: Digital ArchiteX
Author-email: mrvnrmro@gmail.com
Project-URL: Bug Reports, https://github.com/digitalarchitex/darx-core/issues
Project-URL: Source, https://github.com/digitalarchitex/darx-core
Keywords: darx microservices utilities clients
Classifier: Development Status :: 3 - Alpha
Classifier: Intended Audience :: Developers
Classifier: License :: OSI Approved :: MIT License
Classifier: Programming Language :: Python :: 3
Classifier: Programming Language :: Python :: 3.9
Classifier: Programming Language :: Python :: 3.10
Classifier: Programming Language :: Python :: 3.11
Classifier: Programming Language :: Python :: 3.12
Requires-Python: >=3.9
Requires-Dist: supabase>=2.0.0
Requires-Dist: slack-sdk>=3.0.0
Requires-Dist: google-cloud-storage>=2.0.0
Requires-Dist: structlog>=24.0.0
Requires-Dist: requests>=2.31.0
Provides-Extra: dev
Requires-Dist: pytest>=7.0.0; extra == "dev"
Requires-Dist: pytest-cov>=4.0.0; extra == "dev"
Requires-Dist: black>=23.0.0; extra == "dev"
Requires-Dist: flake8>=6.0.0; extra == "dev"
Requires-Dist: mypy>=1.0.0; extra == "dev"
Dynamic: author
Dynamic: author-email
Dynamic: classifier
Dynamic: description
Dynamic: description-content-type
Dynamic: home-page
Dynamic: keywords
Dynamic: project-url
Dynamic: provides-extra
Dynamic: requires-dist
Dynamic: requires-python
Dynamic: summary
